tenrec_capa/__init__.py
tenrec_capa/__main__.py
tenrec_capa/plugins/__init__.py
tenrec_capa/plugins/capa.py
tenrec_capa/plugins/models.py
tenrec_capa-0.1.1.dist-info/METADATA
tenrec_capa-0.1.1.dist-info/WHEEL
tenrec_capa-0.1.1.dist-info/entry_points.txt
tenrec_capa-0.1.1.dist-info/RECORD
