Metadata-Version: 2.4
Name: tenrec-capa
Version: 0.1.1
Summary: A tenrec plugin to integrate with flare-capa.
Author: Axel Mierczuk
License: MIT
Classifier: Development Status :: 5 - Production/Stable
Classifier: Intended Audience :: Developers
Classifier: Operating System :: MacOS
Classifier: Operating System :: Microsoft :: Windows
Classifier: Programming Language :: Python :: 3
Classifier: Programming Language :: Python :: 3.10
Requires-Python: >=3.10
Requires-Dist: flare-capa==9.2.1
Requires-Dist: gitpython>=3.1.45
Requires-Dist: tenrec>=0.1.4
